README.md
setup.cfg
setup.py
src/paul2gans/__init__.py
src/paul2gans.egg-info/PKG-INFO
src/paul2gans.egg-info/SOURCES.txt
src/paul2gans.egg-info/dependency_links.txt
src/paul2gans.egg-info/entry_points.txt
src/paul2gans.egg-info/not-zip-safe
src/paul2gans.egg-info/requires.txt
src/paul2gans.egg-info/top_level.txt
src/paul2gans/images/__init__.py
src/paul2gans/images/generation/__init__.py
src/paul2gans/images/generation/core.py
src/paul2gans/images/visualize/__init__.py
src/paul2gans/models/__init__.py
src/paul2gans/models/training_procedure.py
src/paul2gans/models/discriminators/__init__.py
src/paul2gans/models/discriminators/first_generation.py
src/paul2gans/models/generators/__init__.py
src/paul2gans/models/generators/first_generation.py
src/paul2gans/pipelines/__init__.py
src/paul2gans/pipelines/main.py
src/paul2gans/pipelines/wgan.py
src/paul2gans/tools/__init__.py
src/paul2gans/tools/math_utils.py